fsspec_rclone/__init__.py
fsspec_rclone/_version.py
fsspec_rclone/spec.py
fsspec_rclone-0.0.1.dist-info/LICENSE
fsspec_rclone-0.0.1.dist-info/METADATA
fsspec_rclone-0.0.1.dist-info/WHEEL
fsspec_rclone-0.0.1.dist-info/entry_points.txt
fsspec_rclone-0.0.1.dist-info/top_level.txt
fsspec_rclone-0.0.1.dist-info/RECORD
